another_sudoku_library/__init__.py
another_sudoku_library/generate.py
another_sudoku_library/solve.py
another_sudoku_library/utils.py
another_sudoku_library-0.1.0.dist-info/LICENSE
another_sudoku_library-0.1.0.dist-info/METADATA
another_sudoku_library-0.1.0.dist-info/WHEEL
another_sudoku_library-0.1.0.dist-info/top_level.txt
another_sudoku_library-0.1.0.dist-info/RECORD
