Metadata-Version: 2.1
Name: another-sudoku-library
Version: 0.1.0
Summary: Library for generating and solving Sudoku puzzles.
Home-page: https://github.com/jc400/another_sudoku_library
Author: jc400
License: MIT license
Keywords: sudoku
Platform: UNKNOWN
Classifier: Development Status :: 2 - Pre-Alpha
Classifier: Intended Audience :: Developers
Classifier: License :: OSI Approved :: MIT License
Classifier: Natural Language :: English
Classifier: Programming Language :: Python :: 3
Classifier: Programming Language :: Python :: 3.6
Classifier: Programming Language :: Python :: 3.7
Classifier: Programming Language :: Python :: 3.8
Requires-Python: >=3.6
License-File: LICENSE
